odoo/addons/stock_mts_mto_mrp_rule/README.rst
odoo/addons/stock_mts_mto_mrp_rule/__init__.py
odoo/addons/stock_mts_mto_mrp_rule/__manifest__.py
odoo/addons/stock_mts_mto_mrp_rule/i18n/stock_mts_mto_mrp_rule.pot
odoo/addons/stock_mts_mto_mrp_rule/models/__init__.py
odoo/addons/stock_mts_mto_mrp_rule/models/stock_move.py
odoo/addons/stock_mts_mto_mrp_rule/readme/CONTRIBUTORS.rst
odoo/addons/stock_mts_mto_mrp_rule/readme/DESCRIPTION.rst
odoo/addons/stock_mts_mto_mrp_rule/static/description/icon.png
odoo/addons/stock_mts_mto_mrp_rule/static/description/index.html
odoo/addons/stock_mts_mto_mrp_rule/tests/__init__.py
odoo/addons/stock_mts_mto_mrp_rule/tests/common.py
odoo/addons/stock_mts_mto_mrp_rule/tests/test_stock_move.py
odoo14_addon_stock_mts_mto_mrp_rule-14.0.1.0.1.dist-info/METADATA
odoo14_addon_stock_mts_mto_mrp_rule-14.0.1.0.1.dist-info/WHEEL
odoo14_addon_stock_mts_mto_mrp_rule-14.0.1.0.1.dist-info/top_level.txt
odoo14_addon_stock_mts_mto_mrp_rule-14.0.1.0.1.dist-info/RECORD
